aionyphe/__init__.py
aionyphe/__version__.py
aionyphe/client.py
aionyphe/config.py
aionyphe/enum.py
aionyphe/exception.py
aionyphe/helper.py
aionyphe/logging.py
aionyphe/main.py
aionyphe-3.0.2.dist-info/licenses/LICENSE
aionyphe-3.0.2.dist-info/METADATA
aionyphe-3.0.2.dist-info/WHEEL
aionyphe-3.0.2.dist-info/entry_points.txt
aionyphe-3.0.2.dist-info/top_level.txt
aionyphe-3.0.2.dist-info/RECORD
