Metadata-Version: 2.4
Name: aionyphe
Version: 3.0.2
Summary: Asynchronous Onyphe API and CLI
Author-email: koromodako <koromodako@gmail.com>
License-Expression: MIT
Project-URL: Homepage, https://github.com/koromodako/aionyphe
Project-URL: Repository, https://github.com/koromodako/aionyphe
Project-URL: Bug Tracker, https://github.com/koromodako/aionyphe/issues
Keywords: onyphe,api,cli,asyncio
Classifier: Development Status :: 4 - Beta
Classifier: Intended Audience :: Developers
Classifier: Intended Audience :: End Users/Desktop
Classifier: Natural Language :: English
Classifier: Operating System :: OS Independent
Classifier: Programming Language :: Python :: 3
Classifier: Programming Language :: Python :: 3 :: Only
Classifier: Topic :: Utilities
Requires-Python: >=3.10
License-File: LICENSE
Requires-Dist: rich~=14.2
Requires-Dist: aiodns~=3.5
Requires-Dist: aiohttp~=3.13
Dynamic: license-file
